rocket/__init__.py
rocket/rocket.py
rocketumei812-1.0.0.dist-info/LICENSE.txt
rocketumei812-1.0.0.dist-info/METADATA
rocketumei812-1.0.0.dist-info/WHEEL
rocketumei812-1.0.0.dist-info/top_level.txt
rocketumei812-1.0.0.dist-info/RECORD
