Metadata-Version: 2.1
Name: rocketumei812
Version: 1.0.0
Summary: An awesome package that does something
Home-page: http://pypi.python.org/pypi/ROCKET/
Author: iZALLA
Author-email: i.zalla@esi-sba.dz
License: LICENSE.txt
License-File: LICENSE.txt
